danilo_planner/__init__.py
danilo_planner/gpt4.py
danilo_planner/midirectorio.py
ia_planner_danilo-0.3.dist-info/METADATA
ia_planner_danilo-0.3.dist-info/WHEEL
ia_planner_danilo-0.3.dist-info/top_level.txt
ia_planner_danilo-0.3.dist-info/RECORD
